scipion/__init__.py
scipion/__main__.py
scipion/_version.py
scipion/constants.py
scipion/guiplugin.py
scipion/utils.py
scipion/install/__init__.py
scipion/install/change_rpath.py
scipion/install/clean.py
scipion/install/find_deps.py
scipion/install/funcs.py
scipion/install/inspect_plugins.py
scipion/install/install_plugin.py
scipion/install/plugin_funcs.py
scipion/install/plugin_manager.py
scipion/install/requirements.txt
scipion/install/update_manager.py
scipion/scripts/__init__.py
scipion/scripts/config.py
scipion/scripts/fontbrowser.py
scipion/scripts/kickoff.py
scipion/scripts/tutorial.py
scipion/templates/hosts.template
scipion/templates/protocols.template
scipion/templates/scipion.template
scipion/templates/scipionbox.template
scipion/templates/workflow_betagal1.json
scipion/templates/workflow_betagal2.json
scipion/templates/workflow_tutorial_intro.json
scipion/tests/installation.py
scipion_app_spfluo-0.1.0.dist-info/METADATA
scipion_app_spfluo-0.1.0.dist-info/WHEEL
scipion_app_spfluo-0.1.0.dist-info/entry_points.txt
scipion_app_spfluo-0.1.0.dist-info/licenses/LICENSE.txt
scipion_app_spfluo-0.1.0.dist-info/RECORD
