Metadata-Version: 2.3
Name: scipion-app-spfluo
Version: 0.1.0
Summary: Scipion application. For processing cryo electron microscopy images and hybrid modelling. Fork for the needs of spfluo-app.
Project-URL: Homepage, https://github.com/scipion-em/scipion-app
Author-email: Scipion team <scipion@cnb.csic.es>
Keywords: imageprocessing,scipion,scipion-3.0
Classifier: Programming Language :: Python :: 3
Classifier: Programming Language :: Python :: 3.7
Classifier: Programming Language :: Python :: 3.8
Classifier: Programming Language :: Python :: 3.9
Classifier: Programming Language :: Python :: 3.10
Requires-Python: >=3.6
Requires-Dist: outdated==0.2.2
Requires-Dist: pip
Requires-Dist: scipion-fluo
Requires-Dist: typing-extensions
